argo_dsl/__init__.py
argo_dsl-0.1.dev1.dist-info/LICENSE
argo_dsl-0.1.dev1.dist-info/WHEEL
argo_dsl-0.1.dev1.dist-info/METADATA
argo_dsl-0.1.dev1.dist-info/RECORD
